telegraf_pyplug/__init__.py
telegraf_pyplug/common.py
telegraf_pyplug/py.typed
telegraf_pyplug/test_common.py
telegraf_pyplug-0.1.1.dist-info/LICENSE
telegraf_pyplug-0.1.1.dist-info/METADATA
telegraf_pyplug-0.1.1.dist-info/WHEEL
telegraf_pyplug-0.1.1.dist-info/top_level.txt
telegraf_pyplug-0.1.1.dist-info/RECORD
